OnJava8Zhongwenban/README.md
OnJava8Zhongwenban/__init__.py
OnJava8Zhongwenban/__main__.py
OnJava8Zhongwenban/file.epub
OnJava8Zhongwenban/index.html
OnJava8Zhongwenban/css/__init__.py
OnJava8Zhongwenban/css/annotations.css
OnJava8Zhongwenban/css/main.css
OnJava8Zhongwenban/css/normalize.css
OnJava8Zhongwenban/css/popup.css
OnJava8Zhongwenban/font/__init__.py
OnJava8Zhongwenban/font/fontello.eot
OnJava8Zhongwenban/font/fontello.svg
OnJava8Zhongwenban/font/fontello.ttf
OnJava8Zhongwenban/font/fontello.woff
OnJava8Zhongwenban/img/__init__.py
OnJava8Zhongwenban/img/annotator-glyph-sprite.png
OnJava8Zhongwenban/img/annotator-icon-sprite.png
OnJava8Zhongwenban/img/apple-touch-icon.png
OnJava8Zhongwenban/img/cancelfullscreen.png
OnJava8Zhongwenban/img/close.png
OnJava8Zhongwenban/img/fullscreen.png
OnJava8Zhongwenban/img/loader.gif
OnJava8Zhongwenban/img/menu-icon.png
OnJava8Zhongwenban/img/save.png
OnJava8Zhongwenban/img/saved.png
OnJava8Zhongwenban/img/settings-s.png
OnJava8Zhongwenban/img/settings.png
OnJava8Zhongwenban/img/star.png
OnJava8Zhongwenban/js/__init__.py
OnJava8Zhongwenban/js/epub.js
OnJava8Zhongwenban/js/epub.min.js
OnJava8Zhongwenban/js/epub.min.map
OnJava8Zhongwenban/js/hooks.min.js
OnJava8Zhongwenban/js/hooks.min.map
OnJava8Zhongwenban/js/reader.js
OnJava8Zhongwenban/js/reader.js.map
OnJava8Zhongwenban/js/reader.min.js
OnJava8Zhongwenban/js/reader.min.map
OnJava8Zhongwenban/js/hooks/__init__.py
OnJava8Zhongwenban/js/hooks/extensions/__init__.py
OnJava8Zhongwenban/js/hooks/extensions/highlight.js
OnJava8Zhongwenban/js/libs/__init__.py
OnJava8Zhongwenban/js/libs/jquery.min.js
OnJava8Zhongwenban/js/libs/localforage.min.js
OnJava8Zhongwenban/js/libs/screenfull.js
OnJava8Zhongwenban/js/libs/screenfull.min.js
OnJava8Zhongwenban/js/libs/zip.min.js
OnJava8Zhongwenban/js/plugins/__init__.py
OnJava8Zhongwenban/js/plugins/hypothesis.js
OnJava8Zhongwenban/js/plugins/search.js
on_java_8_zhongwenban-2024.3.4.0.dist-info/METADATA
on_java_8_zhongwenban-2024.3.4.0.dist-info/WHEEL
on_java_8_zhongwenban-2024.3.4.0.dist-info/entry_points.txt
on_java_8_zhongwenban-2024.3.4.0.dist-info/top_level.txt
on_java_8_zhongwenban-2024.3.4.0.dist-info/RECORD
